<Properties StartupConfiguration="{CE9B2838-BAA5-58C9-FABF-B8A8DCBCAB94}|">
  <MonoDevelop.Ide.Workbench ActiveDocument="Assets/Scripts/Game/GameData/GameDataMgr.cs">
    <Files>
      <File FileName="Assets/Scripts/Game/Main/Main.cs" Line="11" Column="11" />
      <File FileName="Assets/Scripts/Game/GameData/GameDataMgr.cs" Line="46" Column="1" />
    </Files>
  </MonoDevelop.Ide.Workbench>
  <MonoDevelop.Ide.DebuggingService.PinnedWatches />
  <MonoDevelop.Ide.Workspace ActiveConfiguration="Debug" />
  <MonoDevelop.Ide.ItemProperties.Assembly-CSharp PreferredExecutionTarget="569d5e1d-5352-4861-82c8-8df36c338aac" />
  <MonoDevelop.Ide.DebuggingService.Breakpoints>
    <BreakpointStore />
  </MonoDevelop.Ide.DebuggingService.Breakpoints>
  <MultiItemStartupConfigurations />
</Properties>